{
  "legislative_session": "119",
  "identifier": "HR 4537",
  "title": "To amend the Internal Revenue Code of 1986 to allow a credit against tax for expenses relating to the purchase and installation of qualified emissions control devices on or in connection with qualified cook stoves or qualified char broilers of eligible small restaurant businesses, and for other purposes.",
  "from_organization": "~{\"classification\": \"lower\"}",
  "classification": [
    "bill"
  ],
  "subject": [],
  "abstracts": [],
  "other_titles": [],
  "other_identifiers": [],
  "actions": [
    {
      "description": "Referred to the House Committee on Ways and Means.",
      "date": "2025-07-17T04:00:00+00:00",
      "organization_id": "~{\"classification\": \"lower\"}",
      "classification": [
        "referral-committee"
      ],
      "related_entities": []
    },
    {
      "description": "Introduced in House",
      "date": "2025-07-17T04:00:00+00:00",
      "organization_id": "~{\"classification\": \"lower\"}",
      "classification": [
        "introduction"
      ],
      "related_entities": []
    }
  ],
  "sponsorships": [
    {
      "name": "Ritchie Torres",
      "classification": "primary",
      "entity_type": "person",
      "primary": true,
      "person_id": "~{\"name\": \"Ritchie Torres\"}",
      "organization_id": null
    }
  ],
  "related_bills": [],
  "versions": [],
  "documents": [],
  "citations": [],
  "sources": [
    {
      "url": "https://www.govinfo.gov/bulkdata/BILLSTATUS/119/hr/BILLSTATUS-119hr4537.xml",
      "note": ""
    },
    {
      "url": "https://congress.gov/bill/119th-congress/house-bill/4537",
      "note": ""
    }
  ],
  "extras": {
    "cosponsor_bioguides": [],
    "sponsor_bioguides": [
      "T000486"
    ]
  },
  "jurisdiction": {
    "id": "ocd-jurisdiction/country:us/government",
    "name": "United States",
    "classification": "country",
    "division_id": "ocd-division/country:us"
  },
  "scraped_at": "2025-07-29T23:32:17+00:00",
  "_id": "4366ba40-6cd4-11f0-a587-065053629bd5"
}